terminalgptpro/__init__.py
terminalgptpro/chat.py
terminalgptpro/config.py
terminalgptpro/conversations.py
terminalgptpro/encryption.py
terminalgptpro/main.py
terminalgptpro/phrases.py
terminalgptpro/printer.py
terminalgptpro/terminal/__init__.py
terminalgptpro/terminal/delete.py
terminalgptpro/terminal/install.py
terminalgptpro/terminal/load.py
terminalgptpro/terminal/new.py
terminalgptpro/terminal/one_shot.py
terminalgpt_pro-0.4.0.dist-info/LICENSE
terminalgpt_pro-0.4.0.dist-info/METADATA
terminalgpt_pro-0.4.0.dist-info/WHEEL
terminalgpt_pro-0.4.0.dist-info/entry_points.txt
terminalgpt_pro-0.4.0.dist-info/top_level.txt
terminalgpt_pro-0.4.0.dist-info/RECORD
